_virtualenv_pyenv/__init__.py
_virtualenv_pyenv/discovery.py
virtualenv_pyenv-0.6.0.dist-info/licenses/LICENSE
virtualenv_pyenv-0.6.0.dist-info/METADATA
virtualenv_pyenv-0.6.0.dist-info/WHEEL
virtualenv_pyenv-0.6.0.dist-info/entry_points.txt
virtualenv_pyenv-0.6.0.dist-info/top_level.txt
virtualenv_pyenv-0.6.0.dist-info/zip-safe
virtualenv_pyenv-0.6.0.dist-info/RECORD
