Metadata-Version: 2.4
Name: virtualenv-pyenv
Version: 0.6.0
Summary: A virtualenv Python discovery plugin for pyenv-installed interpreters
Author-email: Dmitry Meyer <me@undef.im>
License-Expression: MIT
Project-URL: Homepage, https://github.com/un-def/virtualenv-pyenv
Project-URL: Repository, https://github.com/un-def/virtualenv-pyenv.git
Project-URL: Changelog, https://github.com/un-def/virtualenv-pyenv/releases
Project-URL: Issues, https://github.com/un-def/virtualenv-pyenv/issues
Keywords: virtualenv,pyenv
Classifier: Development Status :: 4 - Beta
Classifier: Intended Audience :: Developers
Classifier: Topic :: Software Development :: Libraries
Classifier: Topic :: Software Development :: Testing
Classifier: Topic :: Utilities
Classifier: Programming Language :: Python :: 3
Classifier: Programming Language :: Python :: 3.9
Classifier: Programming Language :: Python :: 3.10
Classifier: Programming Language :: Python :: 3.11
Classifier: Programming Language :: Python :: 3.12
Classifier: Programming Language :: Python :: 3.13
Classifier: Programming Language :: Python :: 3.14
Requires-Python: >=3.9
License-File: LICENSE
Requires-Dist: virtualenv>=20.29.0
Requires-Dist: pyenv-inspect<0.6,>=0.5
Dynamic: license-file
